easyssp_import_export/__init__.py
easyssp_import_export/client/__init__.py
easyssp_import_export/client/import_export_client.py
easyssp_import_export/client/py.typed
easyssp_import_export/models/__init__.py
easyssp_import_export/models/upload_response.py
easyssp_import_export_client-1.0.0.dist-info/METADATA
easyssp_import_export_client-1.0.0.dist-info/WHEEL
easyssp_import_export_client-1.0.0.dist-info/licenses/LICENSE
easyssp_import_export_client-1.0.0.dist-info/RECORD
