Metadata-Version: 2.4
Name: easyssp-import-export-client
Version: 1.0.0
Summary: A Python client for importing and exporting SSP (System Structure and Parameterization) models with easySSP.
Project-URL: Homepage, https://www.easy-ssp.com
Project-URL: Release Changelog, https://github.com/exxcellent/easyssp-import-export-client-python/releases
Project-URL: Source, https://github.com/exxcellent/easyssp-import-export-client-python
Author-email: easySSP Dev Team <easyssp-dev@exxcellent.de>
License: MIT
License-File: LICENSE
Keywords: client,easySSP,export,import,python
Classifier: License :: OSI Approved :: MIT License
Classifier: Operating System :: OS Independent
Classifier: Programming Language :: Python :: 3.11
Requires-Python: >=3.11
Requires-Dist: easyssp-utils>=1.0.0
Requires-Dist: pydantic>=2.11.3
